<?xml version="1.0" encoding="UTF-8"?>
<metadata xml:lang="en"><Esri><CreaDate>20130511</CreaDate><CreaTime>16555300</CreaTime><ArcGISFormat>1.0</ArcGISFormat><SyncOnce>TRUE</SyncOnce><DataProperties><lineage><Process ToolSource="c:\program files (x86)\arcgis\desktop10.0\ArcToolbox\Toolboxes\Conversion Tools.tbx\DEMToRaster" Date="20130511" Time="165553">DEMToRaster C:\Users\luser\Downloads\40111b5.dem C:\Users\luser\Documents\ArcGIS\phil\40111b5.tif FLOAT 1</Process></lineage></DataProperties></Esri></metadata>
